luhnmod10
