Metadata-Version: 1.0
Name: luhnmod10
Version: 1.0.2
Summary: A fast and simple in-place implementation of the luhn check algorithm.
Home-page: https://github.com/luhnmod10/python
Author: Leigh McCulloch
Author-email: UNKNOWN
License: MIT
Platform: UNKNOWN
